{
  "generated_at": 1758264371393,
  "match": {
    "id": "EPL-UNKNOWN",
    "kickoff_jst": "",
    "home": {
      "id": "ARS",
      "name": "ARS"
    },
    "away": {
      "id": "AVL",
      "name": "AVL"
    },
    "hashtag": "#ARSAVL"
  },
  "items": [
    {
      "id": "https://bbc.com/sport/football/articles/c5yql64nx20o?at_medium=RSS&at_campaign=rss",
      "ts": 1758263699000,
      "url": "https://bbc.com/sport/football/articles/c5yql64nx20o?at_medium=RSS&at_campaign=rss",
      "domain": "bbc.com",
      "trust": "bbc",
      "tags": [
        "負傷"
      ],
      "players": [],
      "ja": "Hutton urges Rangers chairman to show leadership - gossip",
      "en": "Hutton urges Rangers chairman to show leadership - gossip",
      "text_for_match": "Hutton urges Rangers chairman to show leadership - gossip Under pressure Rangers in the headlines, Celtic hero urges club to push boat out for manager and St Mirren boss responds to critic. Under pressure Rangers in the headlines, Celtic hero urges club to push boat out for manager and St Mirren boss responds to critic.",
      "score_detail": {
        "fresh": 0.9982239667036236,
        "trust": 1,
        "relevance": 0.6666666666666666
      },
      "score": 0.966
    },
    {
      "id": "https://bbc.com/sport/football/articles/cq8ez858kdgo?at_medium=RSS&at_campaign=rss",
      "ts": 1758260073000,
      "url": "https://bbc.com/sport/football/articles/cq8ez858kdgo?at_medium=RSS&at_campaign=rss",
      "domain": "bbc.com",
      "trust": "bbc",
      "tags": [
        "負傷"
      ],
      "players": [],
      "ja": "I locked Coleen out for putting Liverpool flags up - Rooney",
      "en": "I locked Coleen out for putting Liverpool flags up - Rooney",
      "text_for_match": "I locked Coleen out for putting Liverpool flags up - Rooney With the Merseyside derby approaching, former Everton star Wayne Rooney explains how he locked Coleen out for putting up Liverpool flags. With the Merseyside derby approaching, former Everton star Wayne Rooney explains how he locked Coleen out for putting up Liverpool flags.",
      "score_detail": {
        "fresh": 0.9885913922667103,
        "trust": 1,
        "relevance": 0.6666666666666666
      },
      "score": 0.96
    },
    {
      "id": "https://bbc.com/sport/football/videos/c3067ez657ro?at_medium=RSS&at_campaign=rss",
      "ts": 1758229233000,
      "url": "https://bbc.com/sport/football/videos/c3067ez657ro?at_medium=RSS&at_campaign=rss",
      "domain": "bbc.com",
      "trust": "bbc",
      "tags": [
        "好調"
      ],
      "players": [],
      "ja": "Leverkusen snatch draw at Copenhagen thanks to late own goal",
      "en": "Leverkusen snatch draw at Copenhagen thanks to late own goal",
      "text_for_match": "Leverkusen snatch draw at Copenhagen thanks to late own goal Copenhagen's Pantelis Hatzidiakos scores a 91st minute own goal to give Bayer Leverkusen a 2-2 draw in their opening Champions League match after a thrilling finish, which saw three goals scored in the last nine minutes. Copenhagen's Pantelis Hatzidiakos scores a 91st minute own goal to give Bayer Leverkusen a 2-2 draw in their opening Champions League match after a thrilling finish, which saw three goals scored in the last nine minutes. ",
      "score_detail": {
        "fresh": 0.9103320430356221,
        "trust": 1,
        "relevance": 1
      },
      "score": 0.946
    },
    {
      "id": "https://bbc.com/sport/football/articles/cgmz2gjvevko?at_medium=RSS&at_campaign=rss",
      "ts": 1758262387000,
      "url": "https://bbc.com/sport/football/articles/cgmz2gjvevko?at_medium=RSS&at_campaign=rss",
      "domain": "bbc.com",
      "trust": "bbc",
      "tags": [
        "好調"
      ],
      "players": [],
      "ja": "Can Dunfermline halt in-form St Johnstone? Watch on BBC",
      "en": "Can Dunfermline halt in-form St Johnstone? Watch on BBC",
      "text_for_match": "Can Dunfermline halt in-form St Johnstone? Watch on BBC Sportscene's Jonathan Sutherland preview's BBC Scotland's televised Friday night encounter between St Johnstone and Dunfermline Athletic. Sportscene's Jonathan Sutherland preview's BBC Scotland's televised Friday night encounter between St Johnstone and Dunfermline Athletic.",
      "score_detail": {
        "fresh": 0.9947278119467513,
        "trust": 1,
        "relevance": 0.3333333333333333
      },
      "score": 0.93
    },
    {
      "id": "https://bbc.com/sport/articles/cwy9dlqxx2ro?at_medium=RSS&at_campaign=rss",
      "ts": 1758258342000,
      "url": "https://bbc.com/sport/articles/cwy9dlqxx2ro?at_medium=RSS&at_campaign=rss",
      "domain": "bbc.com",
      "trust": "bbc",
      "tags": [
        "負傷"
      ],
      "players": [],
      "ja": "Premier League ticket black market exposed",
      "en": "Premier League ticket black market exposed",
      "text_for_match": "Premier League ticket black market exposed Find out what happened when we tried to attend four Premier League games with tickets from \"unauthorised\" websites. Find out what happened when we tried to attend four Premier League games with tickets from \"unauthorised\" websites.",
      "score_detail": {
        "fresh": 0.9840257742979104,
        "trust": 1,
        "relevance": 0.3333333333333333
      },
      "score": 0.924
    },
    {
      "id": "https://bbc.com/sport/football/videos/c8d76d8vlyzo?at_medium=RSS&at_campaign=rss",
      "ts": 1758258025000,
      "url": "https://bbc.com/sport/football/videos/c8d76d8vlyzo?at_medium=RSS&at_campaign=rss",
      "domain": "bbc.com",
      "trust": "bbc",
      "tags": [
        "負傷"
      ],
      "players": [],
      "ja": "Are black-market tickets out of control?",
      "en": "Are black-market tickets out of control?",
      "text_for_match": "Are black-market tickets out of control? Are black market tickets out of control? BBC Sport journalists investigated whether they could attend four Premier League matches with tickets bought from unauthorised ticket websites. Are black market tickets out of control? BBC Sport journalists investigated whether they could attend four Premier League matches with tickets bought from unauthorised ticket websites.",
      "score_detail": {
        "fresh": 0.9831919546316273,
        "trust": 1,
        "relevance": 0.3333333333333333
      },
      "score": 0.923
    },
    {
      "id": "https://bbc.com/sport/football/videos/c1mxz4p1z8ko?at_medium=RSS&at_campaign=rss",
      "ts": 1758231926000,
      "url": "https://bbc.com/sport/football/videos/c1mxz4p1z8ko?at_medium=RSS&at_campaign=rss",
      "domain": "bbc.com",
      "trust": "bbc",
      "tags": [
        "復帰",
        "好調"
      ],
      "players": [],
      "ja": "Eintracht Frankfurt earn convincing win over Galatasaray",
      "en": "Eintracht Frankfurt earn convincing win over Galatasaray",
      "text_for_match": "Eintracht Frankfurt earn convincing win over Galatasaray Eintracht Frankfurt fight back from conceding an early goal to convincingly beat Galatasaray in their first Champions League game of the season. Eintracht Frankfurt fight back from conceding an early goal to convincingly beat Galatasaray in their first Champions League game of the season.",
      "score_detail": {
        "fresh": 0.9169115202209326,
        "trust": 1,
        "relevance": 0.6666666666666666
      },
      "score": 0.917
    },
    {
      "id": "https://bbc.com/sport/football/videos/ckgy42ryrvyo?at_medium=RSS&at_campaign=rss",
      "ts": 1758229051000,
      "url": "https://bbc.com/sport/football/videos/ckgy42ryrvyo?at_medium=RSS&at_campaign=rss",
      "domain": "bbc.com",
      "trust": "bbc",
      "tags": [
        "好調"
      ],
      "players": [],
      "ja": "Doku 'wizardry' doubles Manchester City's lead against Napoli",
      "en": "Doku 'wizardry' doubles Manchester City's lead against Napoli",
      "text_for_match": "Doku 'wizardry' doubles Manchester City's lead against Napoli Jeremy Doku scores a brilliant individual goal to extend Manchester City's lead against Napoli in the Champions League at the Ethiad Stadium. Jeremy Doku scores a brilliant individual goal to extend Manchester City's lead against Napoli in the Champions League at the Ethiad Stadium. ",
      "score_detail": {
        "fresh": 0.9098890917155583,
        "trust": 1,
        "relevance": 0.6666666666666666
      },
      "score": 0.913
    },
    {
      "id": "https://bbc.com/sport/football/videos/cpd9jl3wn6do?at_medium=RSS&at_campaign=rss",
      "ts": 1758229029000,
      "url": "https://bbc.com/sport/football/videos/cpd9jl3wn6do?at_medium=RSS&at_campaign=rss",
      "domain": "bbc.com",
      "trust": "bbc",
      "tags": [
        "好調"
      ],
      "players": [],
      "ja": "'It had to be him!' - Haaland makes history as City make breakthrough",
      "en": "'It had to be him!' - Haaland makes history as City make breakthrough",
      "text_for_match": "'It had to be him!' - Haaland makes history as City make breakthrough Erling Haaland scores his 50th Champions League goal in just 49 appearances as he heads Manchester City in front against a stubborn Napoli defence in the Champions League at the Etihad Stadium. Erling Haaland scores his 50th Champions League goal in just 49 appearances as he heads Manchester City in front against a stubborn Napoli defence in the Champions League at the Etihad Stadium. ",
      "score_detail": {
        "fresh": 0.9098355627528035,
        "trust": 1,
        "relevance": 0.6666666666666666
      },
      "score": 0.913
    },
    {
      "id": "https://bbc.com/sport/football/articles/cly9m4m3zlvo?at_medium=RSS&at_campaign=rss",
      "ts": 1758261687000,
      "url": "https://bbc.com/sport/football/articles/cly9m4m3zlvo?at_medium=RSS&at_campaign=rss",
      "domain": "bbc.com",
      "trust": "bbc",
      "tags": [],
      "players": [],
      "ja": "Swap Salah for Haaland? The FPL talking point",
      "en": "Swap Salah for Haaland? The FPL talking point",
      "text_for_match": "Swap Salah for Haaland? The FPL talking point Mohamed Salah or Erling Haaland? As is so often the case, choosing between the two superstars is the big talking point among FPL managers this week. Mohamed Salah or Erling Haaland? As is so often the case, choosing between the two superstars is the big talking point among FPL managers this week.",
      "score_detail": {
        "fresh": 0.9928674975605514,
        "trust": 1,
        "relevance": 0
      },
      "score": 0.896
    },
    {
      "id": "https://bbc.com/sport/football/videos/cwylewvdyk1o?at_medium=RSS&at_campaign=rss",
      "ts": 1758261028000,
      "url": "https://bbc.com/sport/football/videos/cwylewvdyk1o?at_medium=RSS&at_campaign=rss",
      "domain": "bbc.com",
      "trust": "bbc",
      "tags": [],
      "players": [],
      "ja": "The rise of Bergvall - midfield maestro from 'football dynasty'",
      "en": "The rise of Bergvall - midfield maestro from 'football dynasty'",
      "text_for_match": "The rise of Bergvall - midfield maestro from 'football dynasty' Lucas Bergvall's former coaches and the Athletic's Jay Harris discuss the midfielder's rise as part of a \"football dynasty\" in Sweden. Lucas Bergvall's former coaches and the Athletic's Jay Harris discuss the midfielder's rise as part of a \"football dynasty\" in Sweden.",
      "score_detail": {
        "fresh": 0.9911193239767286,
        "trust": 1,
        "relevance": 0
      },
      "score": 0.895
    },
    {
      "id": "https://bbc.com/news/articles/c5y49gq7z79o?at_medium=RSS&at_campaign=rss",
      "ts": 1758260930000,
      "url": "https://bbc.com/news/articles/c5y49gq7z79o?at_medium=RSS&at_campaign=rss",
      "domain": "bbc.com",
      "trust": "bbc",
      "tags": [],
      "players": [],
      "ja": "'It's difficult to grieve when you're fighting for justice'",
      "en": "'It's difficult to grieve when you're fighting for justice'",
      "text_for_match": "'It's difficult to grieve when you're fighting for justice' Relatives say their lives are \"on pause\" after further delays to an inquest into the footballer's death. Relatives say their lives are \"on pause\" after further delays to an inquest into the footballer's death.",
      "score_detail": {
        "fresh": 0.9908596158277958,
        "trust": 1,
        "relevance": 0
      },
      "score": 0.895
    },
    {
      "id": "https://bbc.com/sport/football/articles/cjedl85dnpno?at_medium=RSS&at_campaign=rss",
      "ts": 1758259055000,
      "url": "https://bbc.com/sport/football/articles/cjedl85dnpno?at_medium=RSS&at_campaign=rss",
      "domain": "bbc.com",
      "trust": "bbc",
      "tags": [],
      "players": [],
      "ja": "Ferguson on music, memory and dementia projects",
      "en": "Ferguson on music, memory and dementia projects",
      "text_for_match": "Ferguson on music, memory and dementia projects Former Manchester United boss Sir Alex Ferguson tells BBC Breakfast about his love of music and work with dementia charities. Former Manchester United boss Sir Alex Ferguson tells BBC Breakfast about his love of music and work with dementia charities.",
      "score_detail": {
        "fresh": 0.9859037958235882,
        "trust": 1,
        "relevance": 0
      },
      "score": 0.892
    },
    {
      "id": "https://bbc.com/sport/football/videos/cly1r35vrgeo?at_medium=RSS&at_campaign=rss",
      "ts": 1758237611000,
      "url": "https://bbc.com/sport/football/videos/cly1r35vrgeo?at_medium=RSS&at_campaign=rss",
      "domain": "bbc.com",
      "trust": "bbc",
      "tags": [
        "好調"
      ],
      "players": [],
      "ja": "Forbs 'making the difference' for Brugge says Onouha",
      "en": "Forbs 'making the difference' for Brugge says Onouha",
      "text_for_match": "Forbs 'making the difference' for Brugge says Onouha BBC Sport pundit Nedum Onouha analyses Carlos Forbs' impressive performance for Club Brugge as the Belgian side kicked off their Champions League campaign in style with a 4-1 victory over Monaco. BBC Sport pundit Nedum Onouha analyses Carlos Forbs' impressive performance for Club Brugge as the Belgian side kicked off their Champions League campaign in style with a 4-1 victory over Monaco.  ",
      "score_detail": {
        "fresh": 0.9309575560018343,
        "trust": 1,
        "relevance": 0.3333333333333333
      },
      "score": 0.892
    },
    {
      "id": "https://bbc.com/news/articles/c4gw8y847q7o?at_medium=RSS&at_campaign=rss",
      "ts": 1758258451000,
      "url": "https://bbc.com/news/articles/c4gw8y847q7o?at_medium=RSS&at_campaign=rss",
      "domain": "bbc.com",
      "trust": "bbc",
      "tags": [],
      "players": [],
      "ja": "Borussia Dortmund sorry for TikTok 'mocking' woman's stammer",
      "en": "Borussia Dortmund sorry for TikTok 'mocking' woman's stammer",
      "text_for_match": "Borussia Dortmund sorry for TikTok 'mocking' woman's stammer The German football club deleted a video appearing to mock a woman with a stammer. The German football club deleted a video appearing to mock a woman with a stammer.",
      "score_detail": {
        "fresh": 0.9843126453541946,
        "trust": 1,
        "relevance": 0
      },
      "score": 0.891
    },
    {
      "id": "https://bbc.com/sport/football/articles/cvgr499wn4eo?at_medium=RSS&at_campaign=rss",
      "ts": 1758258119000,
      "url": "https://bbc.com/sport/football/articles/cvgr499wn4eo?at_medium=RSS&at_campaign=rss",
      "domain": "bbc.com",
      "trust": "bbc",
      "tags": [],
      "players": [],
      "ja": "Key questions answered about football's black market for tickets",
      "en": "Key questions answered about football's black market for tickets",
      "text_for_match": "Key questions answered about football's black market for tickets A BBC investigation exposes just how easy it is to buy Premier League tickets on the black market. A BBC investigation exposes just how easy it is to buy Premier League tickets on the black market.",
      "score_detail": {
        "fresh": 0.9834391334316874,
        "trust": 1,
        "relevance": 0
      },
      "score": 0.89
    },
    {
      "id": "https://bbc.co.uk/sounds/play/p0m3j07c?at_medium=RSS&at_campaign=rss",
      "ts": 1758258000000,
      "url": "https://bbc.co.uk/sounds/play/p0m3j07c?at_medium=RSS&at_campaign=rss",
      "domain": "bbc.co.uk",
      "trust": "bbc",
      "tags": [],
      "players": [],
      "ja": "The Wayne Rooney Show",
      "en": "The Wayne Rooney Show",
      "text_for_match": "The Wayne Rooney Show Wayne lifts the lid on grudge matches ahead of the Merseyside derby & Arsenal v Man City. Wayne lifts the lid on grudge matches ahead of the Merseyside derby & Arsenal v Man City.",
      "score_detail": {
        "fresh": 0.9831262260483656,
        "trust": 1,
        "relevance": 0
      },
      "score": 0.89
    },
    {
      "id": "https://bbc.com/sport/football/videos/cr709y7e997o?at_medium=RSS&at_campaign=rss",
      "ts": 1758235437000,
      "url": "https://bbc.com/sport/football/videos/cr709y7e997o?at_medium=RSS&at_campaign=rss",
      "domain": "bbc.com",
      "trust": "bbc",
      "tags": [
        "好調"
      ],
      "players": [],
      "ja": "'Best player of the night' - Butt's praise for 'top talent' Rashford",
      "en": "'Best player of the night' - Butt's praise for 'top talent' Rashford",
      "text_for_match": "'Best player of the night' - Butt's praise for 'top talent' Rashford BBC Sport pundits Nicky Butt, Nedum Onouha and Nicky Bandini analyse Marcus Rashford after the England striker scored twice for Barcelona in their victory over Newcastle. BBC Sport pundits Nicky Butt, Nedum Onouha and Nicky Bandini analyse Marcus Rashford after the England striker scored twice for Barcelona in their victory over Newcastle. ",
      "score_detail": {
        "fresh": 0.9255609827671564,
        "trust": 1,
        "relevance": 0.3333333333333333
      },
      "score": 0.889
    },
    {
      "id": "https://bbc.com/sport/football/videos/cddm34qq8yno?at_medium=RSS&at_campaign=rss",
      "ts": 1758233653000,
      "url": "https://bbc.com/sport/football/videos/cddm34qq8yno?at_medium=RSS&at_campaign=rss",
      "domain": "bbc.com",
      "trust": "bbc",
      "tags": [
        "好調"
      ],
      "players": [],
      "ja": "Two goals and three points 'the perfect night' says Rashford",
      "en": "Two goals and three points 'the perfect night' says Rashford",
      "text_for_match": "Two goals and three points 'the perfect night' says Rashford England striker Marcus Rashford says it was 'the perfect night' after he scored twice for Barcelona in their victory against Newcastle in the Champions League. England striker Marcus Rashford says it was 'the perfect night' after he scored twice for Barcelona in their victory against Newcastle in the Champions League. ",
      "score_detail": {
        "fresh": 0.9211558924991087,
        "trust": 1,
        "relevance": 0.3333333333333333
      },
      "score": 0.886
    },
    {
      "id": "https://bbc.com/sport/football/videos/c62n7g4qvzlo?at_medium=RSS&at_campaign=rss",
      "ts": 1758233396000,
      "url": "https://bbc.com/sport/football/videos/c62n7g4qvzlo?at_medium=RSS&at_campaign=rss",
      "domain": "bbc.com",
      "trust": "bbc",
      "tags": [
        "好調"
      ],
      "players": [],
      "ja": "'We need a player like him' - Flick excited to have Rashford",
      "en": "'We need a player like him' - Flick excited to have Rashford",
      "text_for_match": "'We need a player like him' - Flick excited to have Rashford Barcelona boss Hansi Flick says he's 'delighted' to have Marcus Rashford in his squad after the England international scored both goals for the La Liga champions as they beat Newcastle in the Champions League. Barcelona boss Hansi Flick says he's 'delighted' to have Marcus Rashford in his squad after the England international scored both goals for the La Liga champions as they beat Newcastle in the Champions League. ",
      "score_detail": {
        "fresh": 0.9205230327236515,
        "trust": 1,
        "relevance": 0.3333333333333333
      },
      "score": 0.886
    },
    {
      "id": "https://bbc.com/sport/football/articles/cx2pjg4563lo?at_medium=RSS&at_campaign=rss",
      "ts": 1758208024000,
      "url": "https://bbc.com/sport/football/articles/cx2pjg4563lo?at_medium=RSS&at_campaign=rss",
      "domain": "bbc.com",
      "trust": "bbc",
      "tags": [
        "復帰"
      ],
      "players": [],
      "ja": "Mourinho back at Benfica 25 years on - revered but a risk?",
      "en": "Mourinho back at Benfica 25 years on - revered but a risk?",
      "text_for_match": "Mourinho back at Benfica 25 years on - revered but a risk? As Jose Mourinho returns to Benfica after 25 years, is it a risk for both parties with elections looming? As Jose Mourinho returns to Benfica after 25 years, is it a risk for both parties with elections looming?",
      "score_detail": {
        "fresh": 0.86013792503155,
        "trust": 1,
        "relevance": 0.6666666666666666
      },
      "score": 0.883
    },
    {
      "id": "https://bbc.com/sport/football/videos/c0jq40qdegwo?at_medium=RSS&at_campaign=rss",
      "ts": 1758230985000,
      "url": "https://bbc.com/sport/football/videos/c0jq40qdegwo?at_medium=RSS&at_campaign=rss",
      "domain": "bbc.com",
      "trust": "bbc",
      "tags": [
        "好調"
      ],
      "players": [],
      "ja": "Trincao scores twice as Sporting ease past debutants Kairat",
      "en": "Trincao scores twice as Sporting ease past debutants Kairat",
      "text_for_match": "Trincao scores twice as Sporting ease past debutants Kairat Francisco Trincao scores two stunning goals as Sporting beat Champions League debutants Kairat Almaty 4-1 in Lisbon. Francisco Trincao scores two stunning goals as Sporting beat Champions League debutants Kairat Almaty 4-1 in Lisbon.",
      "score_detail": {
        "fresh": 0.9146071025262645,
        "trust": 1,
        "relevance": 0.3333333333333333
      },
      "score": 0.882
    },
    {
      "id": "https://bbc.com/sport/football/videos/c80gpzg7z9po?at_medium=RSS&at_campaign=rss",
      "ts": 1758230360000,
      "url": "https://bbc.com/sport/football/videos/c80gpzg7z9po?at_medium=RSS&at_campaign=rss",
      "domain": "bbc.com",
      "trust": "bbc",
      "tags": [
        "好調"
      ],
      "players": [],
      "ja": "Rashford stars for Barcelona as they beat Newcastle ",
      "en": "Rashford stars for Barcelona as they beat Newcastle ",
      "text_for_match": "Rashford stars for Barcelona as they beat Newcastle  Marcus Rashford enjoys a night to remember at St James' Park as he scores both of Barcelona's goals as they beat Newcastle 2-1 in their opening match of this season's Champions League. Marcus Rashford enjoys a night to remember at St James' Park as he scores both of Barcelona's goals as they beat Newcastle 2-1 in their opening match of this season's Champions League. ",
      "score_detail": {
        "fresh": 0.913079739863696,
        "trust": 1,
        "relevance": 0.3333333333333333
      },
      "score": 0.881
    },
    {
      "id": "https://bbc.com/sport/football/videos/cy4jn42q23eo?at_medium=RSS&at_campaign=rss",
      "ts": 1758229290000,
      "url": "https://bbc.com/sport/football/videos/cy4jn42q23eo?at_medium=RSS&at_campaign=rss",
      "domain": "bbc.com",
      "trust": "bbc",
      "tags": [
        "好調"
      ],
      "players": [],
      "ja": "Grimaldo scores stunner to help Leverkusen secure point at Copenhagen ",
      "en": "Grimaldo scores stunner to help Leverkusen secure point at Copenhagen ",
      "text_for_match": "Grimaldo scores stunner to help Leverkusen secure point at Copenhagen  Spanish international Alejandro Grimaldo scores a brilliant free-kick, his third in two games, to help Bayer Leverkusen secure a 2-2 draw at Copenhagen in the Champions League. Spanish international Alejandro Grimaldo scores a brilliant free-kick, his third in two games, to help Bayer Leverkusen secure a 2-2 draw at Copenhagen in the Champions League. ",
      "score_detail": {
        "fresh": 0.9104708138858509,
        "trust": 1,
        "relevance": 0.3333333333333333
      },
      "score": 0.88
    },
    {
      "id": "https://bbc.com/sport/football/videos/cn4w795xgdwo?at_medium=RSS&at_campaign=rss",
      "ts": 1758229184000,
      "url": "https://bbc.com/sport/football/videos/cn4w795xgdwo?at_medium=RSS&at_campaign=rss",
      "domain": "bbc.com",
      "trust": "bbc",
      "tags": [
        "好調"
      ],
      "players": [],
      "ja": "Rashford scores brilliant double to guide Barcelona past Newcastle",
      "en": "Rashford scores brilliant double to guide Barcelona past Newcastle",
      "text_for_match": "Rashford scores brilliant double to guide Barcelona past Newcastle Marcus Rashford opens his Barcelona account with a header before scoring a brilliant second to help the La Liga champions kick off their Champions League campaign with a 2-0 win against Newcastle at St James' Park. Marcus Rashford opens his Barcelona account with a header before scoring a brilliant second to help the La Liga champions kick off their Champions League campaign with a 2-0 win against Newcastle at St James' Park. ",
      "score_detail": {
        "fresh": 0.9102127657025332,
        "trust": 1,
        "relevance": 0.3333333333333333
      },
      "score": 0.879
    },
    {
      "id": "https://bbc.com/sport/football/videos/cm2dm4vx2klo?at_medium=RSS&at_campaign=rss",
      "ts": 1758203968000,
      "url": "https://bbc.com/sport/football/videos/cm2dm4vx2klo?at_medium=RSS&at_campaign=rss",
      "domain": "bbc.com",
      "trust": "bbc",
      "tags": [
        "好調"
      ],
      "players": [],
      "ja": "When Newcastle beat Barcelona in the Champions League",
      "en": "When Newcastle beat Barcelona in the Champions League",
      "text_for_match": "When Newcastle beat Barcelona in the Champions League Faustino Asprilla scores a hat-trick against Barcelona on Newcastle United's Champions League debut in 1997. Faustino Asprilla scores a hat-trick against Barcelona on Newcastle United's Champions League debut in 1997.",
      "score_detail": {
        "fresh": 0.8508588784488753,
        "trust": 1,
        "relevance": 0.6666666666666666
      },
      "score": 0.877
    },
    {
      "id": "https://bbc.com/sport/football/articles/cvg98pv6vnvo?at_medium=RSS&at_campaign=rss",
      "ts": 1758237948000,
      "url": "https://bbc.com/sport/football/articles/cvg98pv6vnvo?at_medium=RSS&at_campaign=rss",
      "domain": "bbc.com",
      "trust": "bbc",
      "tags": [],
      "players": [],
      "ja": "Sutton's predictions v The Coral, Starsailor, Picture Parlour & AI",
      "en": "Sutton's predictions v The Coral, Starsailor, Picture Parlour & AI",
      "text_for_match": "Sutton's predictions v The Coral, Starsailor, Picture Parlour & AI BBC Sport football expert Chris Sutton takes on celebrity fans of Liverpool and Everton with his predictions for this weekend's Premier League fixtures. BBC Sport football expert Chris Sutton takes on celebrity fans of Liverpool and Everton with his predictions for this weekend's Premier League fixtures.",
      "score_detail": {
        "fresh": 0.9317969115265098,
        "trust": 1,
        "relevance": 0
      },
      "score": 0.859
    },
    {
      "id": "https://bbc.com/sport/football/articles/cq5j8ddj6jno?at_medium=RSS&at_campaign=rss",
      "ts": 1758237399000,
      "url": "https://bbc.com/sport/football/articles/cq5j8ddj6jno?at_medium=RSS&at_campaign=rss",
      "domain": "bbc.com",
      "trust": "bbc",
      "tags": [],
      "players": [],
      "ja": "Why Club Brugge and Belgian football are on the rise",
      "en": "Why Club Brugge and Belgian football are on the rise",
      "text_for_match": "Why Club Brugge and Belgian football are on the rise Belgium's Club Brugge and Union Saint-Gilloise have already made their mark in the Champions League this season - but what's behind their success? Belgium's Club Brugge and Union Saint-Gilloise have already made their mark in the Champions League this season - but what's behind their success?",
      "score_detail": {
        "fresh": 0.9304299215981616,
        "trust": 1,
        "relevance": 0
      },
      "score": 0.858
    },
    {
      "id": "https://bbc.com/sport/football/videos/cjd1y5gme23o?at_medium=RSS&at_campaign=rss",
      "ts": 1758236725000,
      "url": "https://bbc.com/sport/football/videos/cjd1y5gme23o?at_medium=RSS&at_campaign=rss",
      "domain": "bbc.com",
      "trust": "bbc",
      "tags": [],
      "players": [],
      "ja": "How Foden & Doku magic unlocked 10-man Napoli's low block",
      "en": "How Foden & Doku magic unlocked 10-man Napoli's low block",
      "text_for_match": "How Foden & Doku magic unlocked 10-man Napoli's low block BBC Sport pundits Nedum Onouha, Nicky Bandini and Nicky Butt look at how Manchester City adjusted the way they played to beat the low block of 10-man Napoli. BBC Sport pundits Nedum Onouha, Nicky Bandini and Nicky Butt look at how Manchester City adjusted the way they played to beat the low block of 10-man Napoli.",
      "score_detail": {
        "fresh": 0.9287544282727547,
        "trust": 1,
        "relevance": 0
      },
      "score": 0.857
    },
    {
      "id": "https://bbc.com/sport/football/articles/cp8j684pggvo?at_medium=RSS&at_campaign=rss",
      "ts": 1758236449000,
      "url": "https://bbc.com/sport/football/articles/cp8j684pggvo?at_medium=RSS&at_campaign=rss",
      "domain": "bbc.com",
      "trust": "bbc",
      "tags": [],
      "players": [],
      "ja": "Howe praises Newcastle 'heart' - but it only takes them so far",
      "en": "Howe praises Newcastle 'heart' - but it only takes them so far",
      "text_for_match": "Howe praises Newcastle 'heart' - but it only takes them so far Newcastle United showed plenty of spirit in a 2-1 defeat against Barcelona but the hosts were made to rue not taking their chances Newcastle United showed plenty of spirit in a 2-1 defeat against Barcelona but the hosts were made to rue not taking their chances",
      "score_detail": {
        "fresh": 0.9280691922548011,
        "trust": 1,
        "relevance": 0
      },
      "score": 0.857
    },
    {
      "id": "https://bbc.com/sport/football/articles/cn4w7y120zpo?at_medium=RSS&at_campaign=rss",
      "ts": 1758235889000,
      "url": "https://bbc.com/sport/football/articles/cn4w7y120zpo?at_medium=RSS&at_campaign=rss",
      "domain": "bbc.com",
      "trust": "bbc",
      "tags": [],
      "players": [],
      "ja": "Is Rashford on road to redemption at Barcelona after sinking Newcastle?",
      "en": "Is Rashford on road to redemption at Barcelona after sinking Newcastle?",
      "text_for_match": "Is Rashford on road to redemption at Barcelona after sinking Newcastle? Can Marcus Rashford finally take the road to redemption at Barcelona after his stunning display sinks Newcastle in the Champions League, asks chief football writer Phil McNulty? Can Marcus Rashford finally take the road to redemption at Barcelona after his stunning display sinks Newcastle in the Champions League, asks chief football writer Phil McNulty?",
      "score_detail": {
        "fresh": 0.9266804114635364,
        "trust": 1,
        "relevance": 0
      },
      "score": 0.856
    },
    {
      "id": "https://bbc.co.uk/sounds/play/p0m3qv6s?at_medium=RSS&at_campaign=rss",
      "ts": 1758235140000,
      "url": "https://bbc.co.uk/sounds/play/p0m3qv6s?at_medium=RSS&at_campaign=rss",
      "domain": "bbc.co.uk",
      "trust": "bbc",
      "tags": [],
      "players": [],
      "ja": "Football Daily",
      "en": "Football Daily",
      "text_for_match": "Football Daily Mark Chapman has reaction as Newcastle lose to Barcelona & Manchester City beat Napoli Mark Chapman has reaction as Newcastle lose to Barcelona & Manchester City beat Napoli",
      "score_detail": {
        "fresh": 0.9248261652547131,
        "trust": 1,
        "relevance": 0
      },
      "score": 0.855
    },
    {
      "id": "https://bbc.com/sport/football/articles/cd07dzjdk24o?at_medium=RSS&at_campaign=rss",
      "ts": 1758234476000,
      "url": "https://bbc.com/sport/football/articles/cd07dzjdk24o?at_medium=RSS&at_campaign=rss",
      "domain": "bbc.com",
      "trust": "bbc",
      "tags": [],
      "players": [],
      "ja": "Haaland feats 'unheard of' - how striker broke another record",
      "en": "Haaland feats 'unheard of' - how striker broke another record",
      "text_for_match": "Haaland feats 'unheard of' - how striker broke another record Erling Haaland became the quickest player to reach 50 goals in the Champions League and his numbers are described as \"unheard of\" by Phil Foden. Erling Haaland became the quickest player to reach 50 goals in the Champions League and his numbers are described as \"unheard of\" by Phil Foden.",
      "score_detail": {
        "fresh": 0.9231854503246711,
        "trust": 1,
        "relevance": 0
      },
      "score": 0.854
    },
    {
      "id": "https://bbc.com/sport/football/articles/clyq8epyg07o?at_medium=RSS&at_campaign=rss",
      "ts": 1758233839000,
      "url": "https://bbc.com/sport/football/articles/clyq8epyg07o?at_medium=RSS&at_campaign=rss",
      "domain": "bbc.com",
      "trust": "bbc",
      "tags": [],
      "players": [],
      "ja": "Al-Nassr keen on Casemiro - Friday's gossip",
      "en": "Al-Nassr keen on Casemiro - Friday's gossip",
      "text_for_match": "Al-Nassr keen on Casemiro - Friday's gossip Al-Nassr keen on Casemiro, Manchester United in fight to sign Dusan Vlahovic and Real Madrid interested in Micky van de Ven. Al-Nassr keen on Casemiro, Manchester United in fight to sign Dusan Vlahovic and Real Madrid interested in Micky van de Ven.",
      "score_detail": {
        "fresh": 0.9216141869044021,
        "trust": 1,
        "relevance": 0
      },
      "score": 0.853
    },
    {
      "id": "https://bbc.com/sport/football/articles/cn952dvjppqo?at_medium=RSS&at_campaign=rss",
      "ts": 1758233506000,
      "url": "https://bbc.com/sport/football/articles/cn952dvjppqo?at_medium=RSS&at_campaign=rss",
      "domain": "bbc.com",
      "trust": "bbc",
      "tags": [],
      "players": [],
      "ja": "European journey just beginning for 'history makers' Man Utd",
      "en": "European journey just beginning for 'history makers' Man Utd",
      "text_for_match": "European journey just beginning for 'history makers' Man Utd The journey is just beginning for Manchester United - what do they need to do next in the Women's Champions League? The journey is just beginning for Manchester United - what do they need to do next in the Women's Champions League?",
      "score_detail": {
        "fresh": 0.9207938533175484,
        "trust": 1,
        "relevance": 0
      },
      "score": 0.852
    },
    {
      "id": "https://bbc.com/sport/football/articles/c79vqyzlx88o?at_medium=RSS&at_campaign=rss",
      "ts": 1758185034000,
      "url": "https://bbc.com/sport/football/articles/c79vqyzlx88o?at_medium=RSS&at_campaign=rss",
      "domain": "bbc.com",
      "trust": "bbc",
      "tags": [
        "好調"
      ],
      "players": [],
      "ja": "Son claims first MLS hat-trick in LAFC win",
      "en": "Son claims first MLS hat-trick in LAFC win",
      "text_for_match": "Son claims first MLS hat-trick in LAFC win Son Heung-min scores his first Major League Soccer hat-trick as Los Angeles FC win 4-1 at Real Salt Lake on Wednesday. Son Heung-min scores his first Major League Soccer hat-trick as Los Angeles FC win 4-1 at Real Salt Lake on Wednesday.",
      "score_detail": {
        "fresh": 0.808849914898286,
        "trust": 1,
        "relevance": 0.6666666666666666
      },
      "score": 0.852
    },
    {
      "id": "https://bbc.com/sport/football/videos/cly1r3z15d1o?at_medium=RSS&at_campaign=rss",
      "ts": 1758232728000,
      "url": "https://bbc.com/sport/football/videos/cly1r3z15d1o?at_medium=RSS&at_campaign=rss",
      "domain": "bbc.com",
      "trust": "bbc",
      "tags": [],
      "players": [],
      "ja": "Guardiola happy to see 'the Phil Foden that we know'",
      "en": "Guardiola happy to see 'the Phil Foden that we know'",
      "text_for_match": "Guardiola happy to see 'the Phil Foden that we know' Manchester City boss Pep Guardiola says he's been happy to see \"the Phil Foden we know\" in their last two games after his side eased past Napoli in their Champions League opener. Manchester City boss Pep Guardiola says he's been happy to see \"the Phil Foden we know\" in their last two games after his side eased past Napoli in their Champions League opener. ",
      "score_detail": {
        "fresh": 0.9188801228397869,
        "trust": 1,
        "relevance": 0
      },
      "score": 0.851
    },
    {
      "id": "https://bbc.com/sport/football/videos/cly1l016q65o?at_medium=RSS&at_campaign=rss",
      "ts": 1758229604000,
      "url": "https://bbc.com/sport/football/videos/cly1l016q65o?at_medium=RSS&at_campaign=rss",
      "domain": "bbc.com",
      "trust": "bbc",
      "tags": [],
      "players": [],
      "ja": "Record-breaking Haaland helps City beat 10-man Napoli",
      "en": "Record-breaking Haaland helps City beat 10-man Napoli",
      "text_for_match": "Record-breaking Haaland helps City beat 10-man Napoli Erling Haaland breaks another record by becoming the quickest player to score 50 Champions League goals as Manchester City were made to work hard in their opening game victory over Napoli. Erling Haaland breaks another record by becoming the quickest player to score 50 Champions League goals as Manchester City were made to work hard in their opening game victory over Napoli.",
      "score_detail": {
        "fresh": 0.911235650182741,
        "trust": 1,
        "relevance": 0
      },
      "score": 0.847
    },
    {
      "id": "https://bbc.com/sport/football/videos/c80gp0p248xo?at_medium=RSS&at_campaign=rss",
      "ts": 1758229347000,
      "url": "https://bbc.com/sport/football/videos/c80gp0p248xo?at_medium=RSS&at_campaign=rss",
      "domain": "bbc.com",
      "trust": "bbc",
      "tags": [],
      "players": [],
      "ja": "'That's glorious!' - Vanaken's volley completes perfect half for Brugge",
      "en": "'That's glorious!' - Vanaken's volley completes perfect half for Brugge",
      "text_for_match": "'That's glorious!' - Vanaken's volley completes perfect half for Brugge Hans Vanaken hits a wonderful volley to round off a perfect half for Club Brugge, leading 3-0 at half-time against Monaco in their opening game of the Champions League. Hans Vanaken hits a wonderful volley to round off a perfect half for Club Brugge, leading 3-0 at half-time against Monaco in their opening game of the Champions League.",
      "score_detail": {
        "fresh": 0.9106096058902828,
        "trust": 1,
        "relevance": 0
      },
      "score": 0.846
    },
    {
      "id": "https://bbc.com/sport/football/videos/c864gz0g903o?at_medium=RSS&at_campaign=rss",
      "ts": 1758229098000,
      "url": "https://bbc.com/sport/football/videos/c864gz0g903o?at_medium=RSS&at_campaign=rss",
      "domain": "bbc.com",
      "trust": "bbc",
      "tags": [],
      "players": [],
      "ja": "Club Brugge hit Monaco for four in Champions League rout ",
      "en": "Club Brugge hit Monaco for four in Champions League rout ",
      "text_for_match": "Club Brugge hit Monaco for four in Champions League rout  Club Brugge get their 2025-26 Champions League campaign off to a perfect start as they run riot with a 4-1 win against Monaco at the Jan Breydelstadion. Club Brugge get their 2025-26 Champions League campaign off to a perfect start as they run riot with a 4-1 win against Monaco at the Jan Breydelstadion.",
      "score_detail": {
        "fresh": 0.9100034595961382,
        "trust": 1,
        "relevance": 0
      },
      "score": 0.846
    },
    {
      "id": "https://bbc.com/sport/football/articles/cp3v752ezwlo?at_medium=RSS&at_campaign=rss",
      "ts": 1758227124000,
      "url": "https://bbc.com/sport/football/articles/cp3v752ezwlo?at_medium=RSS&at_campaign=rss",
      "domain": "bbc.com",
      "trust": "bbc",
      "tags": [],
      "players": [],
      "ja": "Man Utd co-owner Ratcliffe flies in for Amorim talks",
      "en": "Man Utd co-owner Ratcliffe flies in for Amorim talks",
      "text_for_match": "Man Utd co-owner Ratcliffe flies in for Amorim talks Manchester United co-owner Sir Jim Ratcliffe met head coach Ruben Amorim at the club's Carrington training ground on Thursday. Manchester United co-owner Sir Jim Ratcliffe met head coach Ruben Amorim at the club's Carrington training ground on Thursday.",
      "score_detail": {
        "fresh": 0.9052123635558356,
        "trust": 1,
        "relevance": 0
      },
      "score": 0.843
    },
    {
      "id": "https://bbc.com/sport/football/articles/c0r01j810gwo?at_medium=RSS&at_campaign=rss",
      "ts": 1758174476000,
      "url": "https://bbc.com/sport/football/articles/c0r01j810gwo?at_medium=RSS&at_campaign=rss",
      "domain": "bbc.com",
      "trust": "bbc",
      "tags": [
        "好調"
      ],
      "players": [],
      "ja": "The cult of Asprilla - and the night Newcastle stunned Barcelona",
      "en": "The cult of Asprilla - and the night Newcastle stunned Barcelona",
      "text_for_match": "The cult of Asprilla - and the night Newcastle stunned Barcelona Tino Asprilla scored a hat-trick for Newcastle United against Barcelona in 1997 and will be watching on as the teams meet at St James' Park tonight. Tino Asprilla scored a hat-trick for Newcastle United against Barcelona in 1997 and will be watching on as the teams meet at St James' Park tonight.",
      "score_detail": {
        "fresh": 0.7863322392317955,
        "trust": 1,
        "relevance": 0.6666666666666666
      },
      "score": 0.838
    },
    {
      "id": "https://bbc.com/sport/football/articles/c5y5908qp7yo?at_medium=RSS&at_campaign=rss",
      "ts": 1758197404000,
      "url": "https://bbc.com/sport/football/articles/c5y5908qp7yo?at_medium=RSS&at_campaign=rss",
      "domain": "bbc.com",
      "trust": "bbc",
      "tags": [
        "負傷"
      ],
      "players": [],
      "ja": "Go-kart brawl and SAS kidnap - when team bonding goes wrong",
      "en": "Go-kart brawl and SAS kidnap - when team bonding goes wrong",
      "text_for_match": "Go-kart brawl and SAS kidnap - when team bonding goes wrong Under-fire Rangers manager Russell Martin has taken his squad open-water swimming this week - but away days don't always work out as planned. Under-fire Rangers manager Russell Martin has taken his squad open-water swimming this week - but away days don't always work out as planned.",
      "score_detail": {
        "fresh": 0.8360538074713,
        "trust": 1,
        "relevance": 0.3333333333333333
      },
      "score": 0.835
    },
    {
      "id": "https://bbc.com/sport/football/articles/c7v1rv1v2nno?at_medium=RSS&at_campaign=rss",
      "ts": 1758220208000,
      "url": "https://bbc.com/sport/football/articles/c7v1rv1v2nno?at_medium=RSS&at_campaign=rss",
      "domain": "bbc.com",
      "trust": "bbc",
      "tags": [],
      "players": [],
      "ja": "Wolves boss Pereira signs new three-year deal",
      "en": "Wolves boss Pereira signs new three-year deal",
      "text_for_match": "Wolves boss Pereira signs new three-year deal Wolves manager Vitor Pereira signs a new three-year contract at Molineux. Wolves manager Vitor Pereira signs a new three-year contract at Molineux. ",
      "score_detail": {
        "fresh": 0.888624667880928,
        "trust": 1,
        "relevance": 0
      },
      "score": 0.833
    },
    {
      "id": "https://bbc.com/sport/football/articles/c78n4y9j1lno?at_medium=RSS&at_campaign=rss",
      "ts": 1758193186000,
      "url": "https://bbc.com/sport/football/articles/c78n4y9j1lno?at_medium=RSS&at_campaign=rss",
      "domain": "bbc.com",
      "trust": "bbc",
      "tags": [
        "復帰"
      ],
      "players": [],
      "ja": "Wales return to Newport for Poland friendly",
      "en": "Wales return to Newport for Poland friendly",
      "text_for_match": "Wales return to Newport for Poland friendly Wales will play their first game in front of a Rodney Parade crowd for six years when they host Poland in a friendly on Tuesday, 28 October. Wales will play their first game in front of a Rodney Parade crowd for six years when they host Poland in a friendly on Tuesday, 28 October.",
      "score_detail": {
        "fresh": 0.8266763691191443,
        "trust": 1,
        "relevance": 0.3333333333333333
      },
      "score": 0.829
    },
    {
      "id": "https://bbc.com/sport/football/articles/c3w54x0qzwvo?at_medium=RSS&at_campaign=rss",
      "ts": 1758212711000,
      "url": "https://bbc.com/sport/football/articles/c3w54x0qzwvo?at_medium=RSS&at_campaign=rss",
      "domain": "bbc.com",
      "trust": "bbc",
      "tags": [],
      "players": [],
      "ja": "Mourinho appointed Benfica manager",
      "en": "Mourinho appointed Benfica manager",
      "text_for_match": "Mourinho appointed Benfica manager Benfica appoint Jose Mourinho as their new manager on a deal until the summer of 2027. Benfica appoint Jose Mourinho as their new manager on a deal until the summer of 2027.",
      "score_detail": {
        "fresh": 0.8709866338749455,
        "trust": 1,
        "relevance": 0
      },
      "score": 0.823
    },
    {
      "id": "https://bbc.com/sport/football/articles/c5y4knqz11vo?at_medium=RSS&at_campaign=rss",
      "ts": 1758207985000,
      "url": "https://bbc.com/sport/football/articles/c5y4knqz11vo?at_medium=RSS&at_campaign=rss",
      "domain": "bbc.com",
      "trust": "bbc",
      "tags": [],
      "players": [],
      "ja": "Atletico and Uefa to review 'spit' footage during Liverpool match",
      "en": "Atletico and Uefa to review 'spit' footage during Liverpool match",
      "text_for_match": "Atletico and Uefa to review 'spit' footage during Liverpool match Atletico Madrid will launch an investigation into the mass confrontation that marred their 3-2 Champions League loss at Anfield, with a member of their backroom team appearing to spit into the crowd. Atletico Madrid will launch an investigation into the mass confrontation that marred their 3-2 Champions League loss at Anfield, with a member of their backroom team appearing to spit into the crowd.",
      "score_detail": {
        "fresh": 0.8600482233630874,
        "trust": 1,
        "relevance": 0
      },
      "score": 0.816
    },
    {
      "id": "https://bbc.com/sport/football/articles/cvgj5w2w0e9o?at_medium=RSS&at_campaign=rss",
      "ts": 1758182381000,
      "url": "https://bbc.com/sport/football/articles/cvgj5w2w0e9o?at_medium=RSS&at_campaign=rss",
      "domain": "bbc.com",
      "trust": "bbc",
      "tags": [
        "負傷"
      ],
      "players": [],
      "ja": "No Haaland but Mbeumo in - our FPL team of the week",
      "en": "No Haaland but Mbeumo in - our FPL team of the week",
      "text_for_match": "No Haaland but Mbeumo in - our FPL team of the week It's again a choice between Mohamed Salah and Erling Haaland, and facing Arsenal means the Norwegian misses out. It's again a choice between Mohamed Salah and Erling Haaland, and facing Arsenal means the Norwegian misses out.",
      "score_detail": {
        "fresh": 0.8031317589341762,
        "trust": 1,
        "relevance": 0.3333333333333333
      },
      "score": 0.815
    },
    {
      "id": "https://bbc.com/sport/football/articles/c0ezp304j0qo?at_medium=RSS&at_campaign=rss",
      "ts": 1758203261000,
      "url": "https://bbc.com/sport/football/articles/c0ezp304j0qo?at_medium=RSS&at_campaign=rss",
      "domain": "bbc.com",
      "trust": "bbc",
      "tags": [],
      "players": [],
      "ja": "PFA in talks with Chelsea over Sterling and Disasi",
      "en": "PFA in talks with Chelsea over Sterling and Disasi",
      "text_for_match": "PFA in talks with Chelsea over Sterling and Disasi The Professional Footballers' Association is in talks with Chelsea over the handling of squad outcasts Raheem Sterling and Axel Disasi. The Professional Footballers' Association is in talks with Chelsea over the handling of squad outcasts Raheem Sterling and Axel Disasi.",
      "score_detail": {
        "fresh": 0.8492517265378574,
        "trust": 1,
        "relevance": 0
      },
      "score": 0.81
    },
    {
      "id": "https://bbc.com/sport/football/articles/ce80zmpd2mpo?at_medium=RSS&at_campaign=rss",
      "ts": 1758202249000,
      "url": "https://bbc.com/sport/football/articles/ce80zmpd2mpo?at_medium=RSS&at_campaign=rss",
      "domain": "bbc.com",
      "trust": "bbc",
      "tags": [],
      "players": [],
      "ja": "'Slot-age time' - breaking down Liverpool's late success",
      "en": "'Slot-age time' - breaking down Liverpool's late success",
      "text_for_match": "'Slot-age time' - breaking down Liverpool's late success BBC Sport examines how and why Liverpool's thrilling late winners have come about. BBC Sport examines how and why Liverpool's thrilling late winners have come about.",
      "score_detail": {
        "fresh": 0.846956529955881,
        "trust": 1,
        "relevance": 0
      },
      "score": 0.808
    },
    {
      "id": "https://bbc.com/sport/football/articles/cp3vl0z24yeo?at_medium=RSS&at_campaign=rss",
      "ts": 1758196315000,
      "url": "https://bbc.com/sport/football/articles/cp3vl0z24yeo?at_medium=RSS&at_campaign=rss",
      "domain": "bbc.com",
      "trust": "bbc",
      "tags": [],
      "players": [],
      "ja": "Which countries are set to win extra Champions League places?",
      "en": "Which countries are set to win extra Champions League places?",
      "text_for_match": "Which countries are set to win extra Champions League places? BBC Sport's Ask Me Anything explains which countries are on course to win extra qualification spots for the 2026-27 Champions League campaign BBC Sport's Ask Me Anything explains which countries are on course to win extra qualification spots for the 2026-27 Champions League campaign",
      "score_detail": {
        "fresh": 0.833622609335487,
        "trust": 1,
        "relevance": 0
      },
      "score": 0.8
    },
    {
      "id": "https://bbc.com/sport/football/articles/ckgq65y1gp2o?at_medium=RSS&at_campaign=rss",
      "ts": 1758193473000,
      "url": "https://bbc.com/sport/football/articles/ckgq65y1gp2o?at_medium=RSS&at_campaign=rss",
      "domain": "bbc.com",
      "trust": "bbc",
      "tags": [],
      "players": [],
      "ja": "Bristol City Women taken over by Mercury13",
      "en": "Bristol City Women taken over by Mercury13",
      "text_for_match": "Bristol City Women taken over by Mercury13 Bristol City Women are taken over by multi-club ownership group Mercury13 in a deal described as \"pivotal\" for the WSL 2 club's future. Bristol City Women are taken over by multi-club ownership group Mercury13 in a deal described as \"pivotal\" for the WSL 2 club's future.",
      "score_detail": {
        "fresh": 0.8273110779674748,
        "trust": 1,
        "relevance": 0
      },
      "score": 0.796
    },
    {
      "id": "https://bbc.co.uk/sounds/play/p0m3hpty?at_medium=RSS&at_campaign=rss",
      "ts": 1758178920000,
      "url": "https://bbc.co.uk/sounds/play/p0m3hpty?at_medium=RSS&at_campaign=rss",
      "domain": "bbc.co.uk",
      "trust": "bbc",
      "tags": [],
      "players": [],
      "ja": "Listen: What is the point in a team bonding trip?",
      "en": "Listen: What is the point in a team bonding trip?",
      "text_for_match": "Listen: What is the point in a team bonding trip? Robbie Neilson and Cillian Sheridan join Phil Goodlad to discuss a 'must-win' weekend Robbie Neilson and Cillian Sheridan join Phil Goodlad to discuss a 'must-win' weekend",
      "score_detail": {
        "fresh": 0.7957327995541712,
        "trust": 1,
        "relevance": 0
      },
      "score": 0.777
    },
    {
      "id": "https://bbc.com/sport/football/videos/cwyrqpzwle2o?at_medium=RSS&at_campaign=rss",
      "ts": 1758151304000,
      "url": "https://bbc.com/sport/football/videos/cwyrqpzwle2o?at_medium=RSS&at_campaign=rss",
      "domain": "bbc.com",
      "trust": "bbc",
      "tags": [
        "好調"
      ],
      "players": [],
      "ja": "Getting an aerial view - how Enrique plans to take PSG to the top",
      "en": "Getting an aerial view - how Enrique plans to take PSG to the top",
      "text_for_match": "Getting an aerial view - how Enrique plans to take PSG to the top BBC Sport's Julien Laurens, Jimmy Floyd Hasselbaink and Leon Osman discuss how Luis Enrique continues to take Paris Saint-Germain to new heights after an impressive start to the defence of their Champions League title with victory over Atalanta. BBC Sport's Julien Laurens, Jimmy Floyd Hasselbaink and Leon Osman discuss how Luis Enrique continues to take Paris Saint-Germain to new heights after an impressive start to the defence of their Champions League title with victory over Atalanta. ",
      "score_detail": {
        "fresh": 0.7390852885198012,
        "trust": 1,
        "relevance": 0.3333333333333333
      },
      "score": 0.777
    },
    {
      "id": "https://bbc.com/sport/football/articles/c62ld0pedd8o?at_medium=RSS&at_campaign=rss",
      "ts": 1758175732000,
      "url": "https://bbc.com/sport/football/articles/c62ld0pedd8o?at_medium=RSS&at_campaign=rss",
      "domain": "bbc.com",
      "trust": "bbc",
      "tags": [],
      "players": [],
      "ja": "Champions League not a learning curve for Chelsea - Palmer",
      "en": "Champions League not a learning curve for Chelsea - Palmer",
      "text_for_match": "Champions League not a learning curve for Chelsea - Palmer Cole Palmer says Chelsea do not see this season's Champions League campaign as a \"learning curve\" - because they want to be competitive in it straight away. Cole Palmer says Chelsea do not see this season's Champions League campaign as a \"learning curve\" - because they want to be competitive in it straight away.",
      "score_detail": {
        "fresh": 0.788977787786145,
        "trust": 1,
        "relevance": 0
      },
      "score": 0.773
    },
    {
      "id": "https://bbc.com/sport/football/videos/cre592rpjxpo?at_medium=RSS&at_campaign=rss",
      "ts": 1758108837000,
      "url": "https://bbc.com/sport/football/videos/cre592rpjxpo?at_medium=RSS&at_campaign=rss",
      "domain": "bbc.com",
      "trust": "bbc",
      "tags": [
        "好調"
      ],
      "players": [],
      "ja": "How to stop an in-form Russo - analysis",
      "en": "How to stop an in-form Russo - analysis",
      "text_for_match": "How to stop an in-form Russo - analysis BBC pundits Fara Williams and Rehanne Skinner analyse Alessia Russo's \"impressive\" performance against West Ham. BBC pundits Fara Williams and Rehanne Skinner analyse Alessia Russo's \"impressive\" performance against West Ham. ",
      "score_detail": {
        "fresh": 0.6597420782248731,
        "trust": 1,
        "relevance": 0.6666666666666666
      },
      "score": 0.763
    },
    {
      "id": "https://bbc.com/sport/football/videos/ce80z6zqve1o?at_medium=RSS&at_campaign=rss",
      "ts": 1758147934000,
      "url": "https://bbc.com/sport/football/videos/ce80z6zqve1o?at_medium=RSS&at_campaign=rss",
      "domain": "bbc.com",
      "trust": "bbc",
      "tags": [],
      "players": [],
      "ja": "Are late winners a problem or perfection for Liverpool?",
      "en": "Are late winners a problem or perfection for Liverpool?",
      "text_for_match": "Are late winners a problem or perfection for Liverpool? BBC Sport's Julien Laurens, Jimmy Floyd Hasselbaink and Leon Osman analyse Liverpool's late winner against Atletico Madrid in the Champions League and whether Arne Slot's side are leaving it late too often this season. BBC Sport's Julien Laurens, Jimmy Floyd Hasselbaink and Leon Osman analyse Liverpool's late winner against Atletico Madrid in the Champions League and whether Arne Slot's side are leaving it late too often this season.  ",
      "score_detail": {
        "fresh": 0.7324545872104136,
        "trust": 1,
        "relevance": 0
      },
      "score": 0.739
    },
    {
      "id": "https://bbc.com/sport/football/articles/c98djy05mzro?at_medium=RSS&at_campaign=rss",
      "ts": 1758141428000,
      "url": "https://bbc.com/sport/football/articles/c98djy05mzro?at_medium=RSS&at_campaign=rss",
      "domain": "bbc.com",
      "trust": "bbc",
      "tags": [],
      "players": [],
      "ja": "What's the next step for Gray's Hibs?",
      "en": "What's the next step for Gray's Hibs?",
      "text_for_match": "What's the next step for Gray's Hibs? BBC Scotland analyses a whirlwind year for Hibernian and looks at how David Gray's side can progress. BBC Scotland analyses a whirlwind year for Hibernian and looks at how David Gray's side can progress.",
      "score_detail": {
        "fresh": 0.7198214058571237,
        "trust": 1,
        "relevance": 0
      },
      "score": 0.732
    },
    {
      "id": "https://bbc.com/sport/football/articles/c740wzr28pzo?at_medium=RSS&at_campaign=rss",
      "ts": 1758124313000,
      "url": "https://bbc.com/sport/football/articles/c740wzr28pzo?at_medium=RSS&at_campaign=rss",
      "domain": "bbc.com",
      "trust": "bbc",
      "tags": [],
      "players": [],
      "ja": "A football future without referees, just cameras?",
      "en": "A football future without referees, just cameras?",
      "text_for_match": "A football future without referees, just cameras? Referees could be replaced by artificial intelligence one day, reckons Livingston manager David Martindale. Referees could be replaced by artificial intelligence one day, reckons Livingston manager David Martindale.",
      "score_detail": {
        "fresh": 0.6876187633467532,
        "trust": 1,
        "relevance": 0
      },
      "score": 0.713
    },
    {
      "id": "https://bbc.com/sport/football/articles/c87y3110dnzo?at_medium=RSS&at_campaign=rss",
      "ts": 1758108556000,
      "url": "https://bbc.com/sport/football/articles/c87y3110dnzo?at_medium=RSS&at_campaign=rss",
      "domain": "bbc.com",
      "trust": "bbc",
      "tags": [],
      "players": [],
      "ja": "Man Utd earn more money than ever despite on-pitch struggles",
      "en": "Man Utd earn more money than ever despite on-pitch struggles",
      "text_for_match": "Man Utd earn more money than ever despite on-pitch struggles Manchester United reveal they generated record financial revenue of £666.5m last year despite the poor on-pitch performance of their men's team. Manchester United reveal they generated record financial revenue of £666.5m last year despite the poor on-pitch performance of their men's team.",
      "score_detail": {
        "fresh": 0.6592465050341356,
        "trust": 1,
        "relevance": 0
      },
      "score": 0.696
    },
    {
      "id": "https://bbc.com/sport/football/articles/cy85x9ywnjxo?at_medium=RSS&at_campaign=rss",
      "ts": 1757999406000,
      "url": "https://bbc.com/sport/football/articles/cy85x9ywnjxo?at_medium=RSS&at_campaign=rss",
      "domain": "bbc.com",
      "trust": "bbc",
      "tags": [
        "負傷",
        "復帰"
      ],
      "players": [],
      "ja": "Ten teenage stars to look out for in Champions League",
      "en": "Ten teenage stars to look out for in Champions League",
      "text_for_match": "Ten teenage stars to look out for in Champions League The Champions League is back this week and BBC Sport has taken a look at 10 teenagers who will be aiming to impress this season. The Champions League is back this week and BBC Sport has taken a look at 10 teenagers who will be aiming to impress this season.",
      "score_detail": {
        "fresh": 0.4923603626423854,
        "trust": 1,
        "relevance": 1
      },
      "score": 0.695
    },
    {
      "id": "https://bbc.com/sport/football/articles/c1kwmjxwpkxo?at_medium=RSS&at_campaign=rss",
      "ts": 1758020325000,
      "url": "https://bbc.com/sport/football/articles/c1kwmjxwpkxo?at_medium=RSS&at_campaign=rss",
      "domain": "bbc.com",
      "trust": "bbc",
      "tags": [
        "復帰"
      ],
      "players": [],
      "ja": "Who will win Champions League? BBC Sport experts make predictions",
      "en": "Who will win Champions League? BBC Sport experts make predictions",
      "text_for_match": "Who will win Champions League? BBC Sport experts make predictions As the Champions League returns on Tuesday, BBC Sport experts predict their winners, which English team will go furthest, a surprise package and most exciting player to watch. As the Champions League returns on Tuesday, BBC Sport experts predict their winners, which English team will go furthest, a surprise package and most exciting player to watch.",
      "score_detail": {
        "fresh": 0.5206885352507206,
        "trust": 1,
        "relevance": 0.3333333333333333
      },
      "score": 0.646
    },
    {
      "id": "https://bbc.com/sport/football/articles/c1dqe1g30lvo?at_medium=RSS&at_campaign=rss",
      "ts": 1758047193000,
      "url": "https://bbc.com/sport/football/articles/c1dqe1g30lvo?at_medium=RSS&at_campaign=rss",
      "domain": "bbc.com",
      "trust": "bbc",
      "tags": [],
      "players": [],
      "ja": "Pundits focused on £450m spend 'favour other clubs' - Slot",
      "en": "Pundits focused on £450m spend 'favour other clubs' - Slot",
      "text_for_match": "Pundits focused on £450m spend 'favour other clubs' - Slot Liverpool manager Arne Slot criticises pundits who \"favour other clubs\" for their comments over the club's summer spending. Liverpool manager Arne Slot criticises pundits who \"favour other clubs\" for their comments over the club's summer spending.",
      "score_detail": {
        "fresh": 0.5594766994966383,
        "trust": 1,
        "relevance": 0
      },
      "score": 0.636
    },
    {
      "id": "https://bbc.com/sport/football/articles/c0ew9qnv9dqo?at_medium=RSS&at_campaign=rss",
      "ts": 1758031886000,
      "url": "https://bbc.com/sport/football/articles/c0ew9qnv9dqo?at_medium=RSS&at_campaign=rss",
      "domain": "bbc.com",
      "trust": "bbc",
      "tags": [],
      "players": [],
      "ja": "What is meldonium and can it enhance a footballer's performance?",
      "en": "What is meldonium and can it enhance a footballer's performance?",
      "text_for_match": "What is meldonium and can it enhance a footballer's performance? Meldonium use has led to significant bans for several prominent athletes. Meldonium use has led to significant bans for several prominent athletes.",
      "score_detail": {
        "fresh": 0.5370376612149019,
        "trust": 1,
        "relevance": 0
      },
      "score": 0.622
    },
    {
      "id": "https://bbc.com/sport/football/articles/c5y8g1mgrp0o?at_medium=RSS&at_campaign=rss",
      "ts": 1758022001000,
      "url": "https://bbc.com/sport/football/articles/c5y8g1mgrp0o?at_medium=RSS&at_campaign=rss",
      "domain": "bbc.com",
      "trust": "bbc",
      "tags": [],
      "players": [],
      "ja": "DeMelo 'in good spirits' after collapsing on pitch",
      "en": "DeMelo 'in good spirits' after collapsing on pitch",
      "text_for_match": "DeMelo 'in good spirits' after collapsing on pitch USA midfielder Savannah DeMelo is \"awake and in good spirits\" in hospital after collapsing on the pitch while playing for Racing Louisville. USA midfielder Savannah DeMelo is \"awake and in good spirits\" in hospital after collapsing on the pitch while playing for Racing Louisville.",
      "score_detail": {
        "fresh": 0.5230274591649986,
        "trust": 1,
        "relevance": 0
      },
      "score": 0.614
    },
    {
      "id": "https://bbc.com/sport/football/articles/cj4y2qk8115o?at_medium=RSS&at_campaign=rss",
      "ts": 1758017303000,
      "url": "https://bbc.com/sport/football/articles/cj4y2qk8115o?at_medium=RSS&at_campaign=rss",
      "domain": "bbc.com",
      "trust": "bbc",
      "tags": [],
      "players": [],
      "ja": "Newcastle apologise to fans over ticket controversy",
      "en": "Newcastle apologise to fans over ticket controversy",
      "text_for_match": "Newcastle apologise to fans over ticket controversy Newcastle United cancel more than 100 season tickets and apologise to supporters after seats sold to tour organisers a decade ago were \"not detected until recently\". Newcastle United cancel more than 100 season tickets and apologise to supporters after seats sold to tour organisers a decade ago were \"not detected until recently\".",
      "score_detail": {
        "fresh": 0.5164976161838839,
        "trust": 1,
        "relevance": 0
      },
      "score": 0.61
    },
    {
      "id": "https://bbc.com/sport/football/articles/cwy9we7vn17o?at_medium=RSS&at_campaign=rss",
      "ts": 1757994751000,
      "url": "https://bbc.com/sport/football/articles/cwy9we7vn17o?at_medium=RSS&at_campaign=rss",
      "domain": "bbc.com",
      "trust": "bbc",
      "tags": [],
      "players": [],
      "ja": "Ingle seeks confidence and Wales caps in Bristol",
      "en": "Ingle seeks confidence and Wales caps in Bristol",
      "text_for_match": "Ingle seeks confidence and Wales caps in Bristol Wales midfielder Sophie Ingle targets promotion and a regaining of confidence with Bristol City Wales midfielder Sophie Ingle targets promotion and a regaining of confidence with Bristol City",
      "score_detail": {
        "fresh": 0.4862693020257446,
        "trust": 1,
        "relevance": 0
      },
      "score": 0.592
    },
    {
      "id": "https://bbc.com/sport/football/videos/c5y8g68y63po?at_medium=RSS&at_campaign=rss",
      "ts": 1757876327000,
      "url": "https://bbc.com/sport/football/videos/c5y8g68y63po?at_medium=RSS&at_campaign=rss",
      "domain": "bbc.com",
      "trust": "bbc",
      "tags": [
        "好調"
      ],
      "players": [],
      "ja": "Haaland scores twice as Man City cruise to win against Man Utd",
      "en": "Haaland scores twice as Man City cruise to win against Man Utd",
      "text_for_match": "Haaland scores twice as Man City cruise to win against Man Utd Manchester City beat rivals Manchester United 3-0, with a goal from Phil Foden followed by two from Erling Haaland at Etihad Stadium. Manchester City beat rivals Manchester United 3-0, with a goal from Phil Foden followed by two from Erling Haaland at Etihad Stadium.",
      "score_detail": {
        "fresh": 0.35427577077585354,
        "trust": 1,
        "relevance": 0.6666666666666666
      },
      "score": 0.579
    },
    {
      "id": "https://bbc.com/sport/football/videos/cy0vy9jyed5o?at_medium=RSS&at_campaign=rss",
      "ts": 1757876323000,
      "url": "https://bbc.com/sport/football/videos/cy0vy9jyed5o?at_medium=RSS&at_campaign=rss",
      "domain": "bbc.com",
      "trust": "bbc",
      "tags": [
        "好調"
      ],
      "players": [],
      "ja": "Salah scores dramatic late penalty to beat Burnley",
      "en": "Salah scores dramatic late penalty to beat Burnley",
      "text_for_match": "Salah scores dramatic late penalty to beat Burnley Liverpool remain unbeaten as they win 1-0 against Burnley after Mohamed Salah's stoppage time penalty at Turf Moor. Liverpool remain unbeaten as they win 1-0 against Burnley after Mohamed Salah's stoppage time penalty at Turf Moor.",
      "score_detail": {
        "fresh": 0.3542719812089046,
        "trust": 1,
        "relevance": 0.6666666666666666
      },
      "score": 0.579
    },
    {
      "id": "https://bbc.com/sport/football/articles/c7847dy555zo?at_medium=RSS&at_campaign=rss",
      "ts": 1757946853000,
      "url": "https://bbc.com/sport/football/articles/c7847dy555zo?at_medium=RSS&at_campaign=rss",
      "domain": "bbc.com",
      "trust": "bbc",
      "tags": [],
      "players": [],
      "ja": "Why are there Champions League games on Thursday?",
      "en": "Why are there Champions League games on Thursday?",
      "text_for_match": "Why are there Champions League games on Thursday? Our Ask Me Anything team look at why some Champions League games are taking place on Thursday. Our Ask Me Anything team look at why some Champions League games are taking place on Thursday.",
      "score_detail": {
        "fresh": 0.4278081156304788,
        "trust": 1,
        "relevance": 0
      },
      "score": 0.557
    },
    {
      "id": "https://bbc.com/sport/football/articles/c8d7gdez5dzo?at_medium=RSS&at_campaign=rss",
      "ts": 1757937401000,
      "url": "https://bbc.com/sport/football/articles/c8d7gdez5dzo?at_medium=RSS&at_campaign=rss",
      "domain": "bbc.com",
      "trust": "bbc",
      "tags": [],
      "players": [],
      "ja": "What is the Champions League anthem?",
      "en": "What is the Champions League anthem?",
      "text_for_match": "What is the Champions League anthem? Our Ask Me Anything team look at how the Champions League anthem was created and what the lyrics are. Our Ask Me Anything team look at how the Champions League anthem was created and what the lyrics are.",
      "score_detail": {
        "fresh": 0.4171302102154717,
        "trust": 1,
        "relevance": 0
      },
      "score": 0.55
    },
    {
      "id": "https://bbc.com/sport/football/videos/czrpv03ye6mo?at_medium=RSS&at_campaign=rss",
      "ts": 1757874812000,
      "url": "https://bbc.com/sport/football/videos/czrpv03ye6mo?at_medium=RSS&at_campaign=rss",
      "domain": "bbc.com",
      "trust": "bbc",
      "tags": [
        "好調"
      ],
      "players": [],
      "ja": "'We need him so much' - Guardiola praises 'incredible' Foden",
      "en": "'We need him so much' - Guardiola praises 'incredible' Foden",
      "text_for_match": "'We need him so much' - Guardiola praises 'incredible' Foden Manchester City manager Pep Guardiola praises Phil Foden and Erling Haaland who both produced impressive performances in their 3-0 derby victory against Manchester United. Manchester City manager Pep Guardiola praises Phil Foden and Erling Haaland who both produced impressive performances in their 3-0 derby victory against Manchester United.",
      "score_detail": {
        "fresh": 0.35284336818110246,
        "trust": 1,
        "relevance": 0.3333333333333333
      },
      "score": 0.545
    },
    {
      "id": "https://bbc.com/sport/football/videos/c75qd557215o?at_medium=RSS&at_campaign=rss",
      "ts": 1757926636000,
      "url": "https://bbc.com/sport/football/videos/c75qd557215o?at_medium=RSS&at_campaign=rss",
      "domain": "bbc.com",
      "trust": "bbc",
      "tags": [],
      "players": [],
      "ja": "I am not going to change formation - Amorim",
      "en": "I am not going to change formation - Amorim",
      "text_for_match": "I am not going to change formation - Amorim Manchester United manager Ruben Amorim repeats his commitment to his 3-4-3 formation despite their derby defeat. Manchester United manager Ruben Amorim repeats his commitment to his 3-4-3 formation despite their derby defeat.",
      "score_detail": {
        "fresh": 0.4052932550032763,
        "trust": 1,
        "relevance": 0
      },
      "score": 0.543
    },
    {
      "id": "https://bbc.com/sport/football/videos/c0ezl81znv0o?at_medium=RSS&at_campaign=rss",
      "ts": 1757798915000,
      "url": "https://bbc.com/sport/football/videos/c0ezl81znv0o?at_medium=RSS&at_campaign=rss",
      "domain": "bbc.com",
      "trust": "bbc",
      "tags": [
        "負傷",
        "好調"
      ],
      "players": [],
      "ja": "Carvalho snatches late draw for Brentford against Chelsea",
      "en": "Carvalho snatches late draw for Brentford against Chelsea",
      "text_for_match": "Carvalho snatches late draw for Brentford against Chelsea Watch Premier League highlights as Fabio Carvalho scores an injury-time equaliser for Brentford to earn a 2-2 draw with West London rivals Chelsea. Watch Premier League highlights as Fabio Carvalho scores an injury-time equaliser for Brentford to earn a 2-2 draw with West London rivals Chelsea.",
      "score_detail": {
        "fresh": 0.28802926324207506,
        "trust": 1,
        "relevance": 0.6666666666666666
      },
      "score": 0.539
    },
    {
      "id": "https://bbc.com/sport/football/videos/cj07z8818g3o?at_medium=RSS&at_campaign=rss",
      "ts": 1757798689000,
      "url": "https://bbc.com/sport/football/videos/cj07z8818g3o?at_medium=RSS&at_campaign=rss",
      "domain": "bbc.com",
      "trust": "bbc",
      "tags": [
        "好調"
      ],
      "players": [],
      "ja": "Woltemade scores winning goal on Newcastle debut",
      "en": "Woltemade scores winning goal on Newcastle debut",
      "text_for_match": "Woltemade scores winning goal on Newcastle debut Nick Woltemade scores on his debut for Newcastle United win a 1-0 win against Wolverhampton Wanderers at St James' Park. Nick Woltemade scores on his debut for Newcastle United win a 1-0 win against Wolverhampton Wanderers at St James' Park.",
      "score_detail": {
        "fresh": 0.28785524118940536,
        "trust": 1,
        "relevance": 0.6666666666666666
      },
      "score": 0.539
    },
    {
      "id": "https://bbc.com/sport/football/videos/c1l8plz9jdyo?at_medium=RSS&at_campaign=rss",
      "ts": 1757798681000,
      "url": "https://bbc.com/sport/football/videos/c1l8plz9jdyo?at_medium=RSS&at_campaign=rss",
      "domain": "bbc.com",
      "trust": "bbc",
      "tags": [
        "好調"
      ],
      "players": [],
      "ja": "Semenyo shines as Bournemouth beat Brighton",
      "en": "Semenyo shines as Bournemouth beat Brighton",
      "text_for_match": "Semenyo shines as Bournemouth beat Brighton Antoine Semenyo chips in with a goal and an assist in Bournemouth's 2-1 win against Brighton & Hove Albion at the Vitality Stadium. Antoine Semenyo chips in with a goal and an assist in Bournemouth's 2-1 win against Brighton & Hove Albion at the Vitality Stadium.",
      "score_detail": {
        "fresh": 0.28784908304389356,
        "trust": 1,
        "relevance": 0.6666666666666666
      },
      "score": 0.539
    },
    {
      "id": "https://bbc.com/sport/football/videos/c62qg444m2no?at_medium=RSS&at_campaign=rss",
      "ts": 1757798669000,
      "url": "https://bbc.com/sport/football/videos/c62qg444m2no?at_medium=RSS&at_campaign=rss",
      "domain": "bbc.com",
      "trust": "bbc",
      "tags": [
        "好調"
      ],
      "players": [],
      "ja": "Late goal earns Fulham first league win of the season",
      "en": "Late goal earns Fulham first league win of the season",
      "text_for_match": "Late goal earns Fulham first league win of the season Leeds United's Gabriel Gudmundsson scores an unfortunate own goal in stoppage time to gift Fulham their first league win of the season. Leeds United's Gabriel Gudmundsson scores an unfortunate own goal in stoppage time to gift Fulham their first league win of the season.",
      "score_detail": {
        "fresh": 0.2878398460726421,
        "trust": 1,
        "relevance": 0.6666666666666666
      },
      "score": 0.539
    },
    {
      "id": "https://bbc.com/sport/football/videos/cx278487m8jo?at_medium=RSS&at_campaign=rss",
      "ts": 1757918396000,
      "url": "https://bbc.com/sport/football/videos/cx278487m8jo?at_medium=RSS&at_campaign=rss",
      "domain": "bbc.com",
      "trust": "bbc",
      "tags": [],
      "players": [],
      "ja": "Should Liverpool worry about Salah's dip in form?",
      "en": "Should Liverpool worry about Salah's dip in form?",
      "text_for_match": "Should Liverpool worry about Salah's dip in form? MOTD pundits Danny Murphy and Theo Walcott believe Mohamed Salah is showing \"positive habits\" despite not having been at his electric best so far this season. MOTD pundits Danny Murphy and Theo Walcott believe Mohamed Salah is showing \"positive habits\" despite not having been at his electric best so far this season.",
      "score_detail": {
        "fresh": 0.39646019973837865,
        "trust": 1,
        "relevance": 0
      },
      "score": 0.538
    },
    {
      "id": "https://bbc.com/sport/football/articles/c1wgdngrpqro?at_medium=RSS&at_campaign=rss",
      "ts": 1757795819000,
      "url": "https://bbc.com/sport/football/articles/c1wgdngrpqro?at_medium=RSS&at_campaign=rss",
      "domain": "bbc.com",
      "trust": "bbc",
      "tags": [
        "好調"
      ],
      "players": [],
      "ja": "'Stick together' - but will Potter get more time at West Ham?",
      "en": "'Stick together' - but will Potter get more time at West Ham?",
      "text_for_match": "'Stick together' - but will Potter get more time at West Ham? Two defeats, eight goals conceded and just the solitary goal scored on home soil makes miserable reading for Graham Potter that is only going to increase the pressure he is under at West Ham. Two defeats, eight goals conceded and just the solitary goal scored on home soil makes miserable reading for Graham Potter that is only going to increase the pressure he is under at West Ham.",
      "score_detail": {
        "fresh": 0.28565443911921323,
        "trust": 1,
        "relevance": 0.6666666666666666
      },
      "score": 0.538
    },
    {
      "id": "https://bbc.com/sport/football/videos/cr708xn4n4mo?at_medium=RSS&at_campaign=rss",
      "ts": 1757891181000,
      "url": "https://bbc.com/sport/football/videos/cr708xn4n4mo?at_medium=RSS&at_campaign=rss",
      "domain": "bbc.com",
      "trust": "bbc",
      "tags": [],
      "players": [],
      "ja": "Is Man Utd's 'shoehorned' team selection costing them?",
      "en": "Is Man Utd's 'shoehorned' team selection costing them?",
      "text_for_match": "Is Man Utd's 'shoehorned' team selection costing them? Match Of The Day pundit Danny Murphy believes Manchester United do not have the personnel needed to play Ruben Amorim's 3-4-3 system, highlighting the performances of Bruno Fernandes and Luke Shaw in their 3-0 loss to rivals Manchester City. Match Of The Day pundit Danny Murphy believes Manchester United do not have the personnel needed to play Ruben Amorim's 3-4-3 system, highlighting the performances of Bruno Fernandes and Luke Shaw in their 3-0 loss to rivals Manchester City.",
      "score_detail": {
        "fresh": 0.3686316390517925,
        "trust": 1,
        "relevance": 0
      },
      "score": 0.521
    },
    {
      "id": "https://bbc.com/sport/football/articles/crrjzpvjk8jo?at_medium=RSS&at_campaign=rss",
      "ts": 1757887755000,
      "url": "https://bbc.com/sport/football/articles/crrjzpvjk8jo?at_medium=RSS&at_campaign=rss",
      "domain": "bbc.com",
      "trust": "bbc",
      "tags": [],
      "players": [],
      "ja": "The Englishman leading Messi in Golden Boot race",
      "en": "The Englishman leading Messi in Golden Boot race",
      "text_for_match": "The Englishman leading Messi in Golden Boot race Lionel Messi has had various memorable Golden Boot battles in the past - usually with Cristiano Ronaldo - but he has a new rival in Englishman Sam Surridge. Lionel Messi has had various memorable Golden Boot battles in the past - usually with Cristiano Ronaldo - but he has a new rival in Englishman Sam Surridge.",
      "score_detail": {
        "fresh": 0.3652697567667559,
        "trust": 1,
        "relevance": 0
      },
      "score": 0.519
    },
    {
      "id": "https://bbc.com/sport/football/articles/cqlz67elveyo?at_medium=RSS&at_campaign=rss",
      "ts": 1757881633000,
      "url": "https://bbc.com/sport/football/articles/cqlz67elveyo?at_medium=RSS&at_campaign=rss",
      "domain": "bbc.com",
      "trust": "bbc",
      "tags": [],
      "players": [],
      "ja": "Who has made Troy's Premier League team of the week?",
      "en": "Who has made Troy's Premier League team of the week?",
      "text_for_match": "Who has made Troy's Premier League team of the week? After every round of Premier League matches this season, Troy Deeney gives us his team of the week. Do you agree with his choices? After every round of Premier League matches this season, Troy Deeney gives us his team of the week. Do you agree with his choices?",
      "score_detail": {
        "fresh": 0.35933849123817624,
        "trust": 1,
        "relevance": 0
      },
      "score": 0.516
    },
    {
      "id": "https://bbc.com/sport/football/articles/cg421g3x743o?at_medium=RSS&at_campaign=rss",
      "ts": 1757878626000,
      "url": "https://bbc.com/sport/football/articles/cg421g3x743o?at_medium=RSS&at_campaign=rss",
      "domain": "bbc.com",
      "trust": "bbc",
      "tags": [],
      "players": [],
      "ja": "'Better than Treble year' - when could Haaland beat Shearer's record?",
      "en": "'Better than Treble year' - when could Haaland beat Shearer's record?",
      "text_for_match": "'Better than Treble year' - when could Haaland beat Shearer's record? The sight of a rampant Erling Haaland with a beaming smile on his face will be of great comfort to both Manchester City and boss Pep Guardiola after a \"complete performance\" against Manchester United. The sight of a rampant Erling Haaland with a beaming smile on his face will be of great comfort to both Manchester City and boss Pep Guardiola after a \"complete performance\" against Manchester United.",
      "score_detail": {
        "fresh": 0.35646054507503083,
        "trust": 1,
        "relevance": 0
      },
      "score": 0.514
    },
    {
      "id": "https://bbc.com/sport/football/videos/c9304wg6pz4o?at_medium=RSS&at_campaign=rss",
      "ts": 1757876272000,
      "url": "https://bbc.com/sport/football/videos/c9304wg6pz4o?at_medium=RSS&at_campaign=rss",
      "domain": "bbc.com",
      "trust": "bbc",
      "tags": [],
      "players": [],
      "ja": "Man Utd need to work on a lot of things - Amorim",
      "en": "Man Utd need to work on a lot of things - Amorim",
      "text_for_match": "Man Utd need to work on a lot of things - Amorim Ruben Amorim believes his Manchester United side have a lot of work to do after their 3-0 loss to local rivals Manchester City. Ruben Amorim believes his Manchester United side have a lot of work to do after their 3-0 loss to local rivals Manchester City.\n\n\n",
      "score_detail": {
        "fresh": 0.3542236677833652,
        "trust": 1,
        "relevance": 0
      },
      "score": 0.513
    },
    {
      "id": "https://bbc.com/sport/football/articles/cvgqp6k9237o?at_medium=RSS&at_campaign=rss",
      "ts": 1757803432000,
      "url": "https://bbc.com/sport/football/articles/cvgqp6k9237o?at_medium=RSS&at_campaign=rss",
      "domain": "bbc.com",
      "trust": "bbc",
      "tags": [
        "復帰"
      ],
      "players": [],
      "ja": "Long throws are back - and Brentford are the masters",
      "en": "Long throws are back - and Brentford are the masters",
      "text_for_match": "Long throws are back - and Brentford are the masters Brentford are the masters of the long throw and it showed again with their late equaliser against Chelsea on Saturday. Brentford are the masters of the long throw and it showed again with their late equaliser against Chelsea on Saturday.",
      "score_detail": {
        "fresh": 0.29152954325055064,
        "trust": 1,
        "relevance": 0.3333333333333333
      },
      "score": 0.508
    },
    {
      "id": "https://bbc.com/sport/football/videos/cvgvp2zk785o?at_medium=RSS&at_campaign=rss",
      "ts": 1757798708000,
      "url": "https://bbc.com/sport/football/videos/cvgvp2zk785o?at_medium=RSS&at_campaign=rss",
      "domain": "bbc.com",
      "trust": "bbc",
      "tags": [
        "好調"
      ],
      "players": [],
      "ja": "Zubimendi scores first goals for Arsenal in win over Forest",
      "en": "Zubimendi scores first goals for Arsenal in win over Forest",
      "text_for_match": "Zubimendi scores first goals for Arsenal in win over Forest Martin Zubimendi scores two goals in his Arsenal debut to help beat Nottingham Forest 3-0 at Emirates Stadium. Martin Zubimendi scores two goals in his Arsenal debut to help beat Nottingham Forest 3-0 at Emirates Stadium.",
      "score_detail": {
        "fresh": 0.2878698673130113,
        "trust": 1,
        "relevance": 0.3333333333333333
      },
      "score": 0.506
    },
    {
      "id": "https://bbc.com/sport/football/videos/cqjedj9gve2o?at_medium=RSS&at_campaign=rss",
      "ts": 1757798660000,
      "url": "https://bbc.com/sport/football/videos/cqjedj9gve2o?at_medium=RSS&at_campaign=rss",
      "domain": "bbc.com",
      "trust": "bbc",
      "tags": [
        "好調"
      ],
      "players": [],
      "ja": "Everton miss big chances in draw with Aston Villa",
      "en": "Everton miss big chances in draw with Aston Villa",
      "text_for_match": "Everton miss big chances in draw with Aston Villa Aston Villa are still  yet to score their first Premier League goal of the season after a 0-0 draw with Everton at Hill Dickinson Stadium. Aston Villa are still  yet to score their first Premier League goal of the season after a 0-0 draw with Everton at Hill Dickinson Stadium.",
      "score_detail": {
        "fresh": 0.2878329185387238,
        "trust": 1,
        "relevance": 0.3333333333333333
      },
      "score": 0.506
    },
    {
      "id": "https://bbc.com/sport/football/videos/ckgzng8m7ero?at_medium=RSS&at_campaign=rss",
      "ts": 1757798637000,
      "url": "https://bbc.com/sport/football/videos/ckgzng8m7ero?at_medium=RSS&at_campaign=rss",
      "domain": "bbc.com",
      "trust": "bbc",
      "tags": [
        "負傷"
      ],
      "players": [],
      "ja": "Crystal Palace and Sunderland play out scrappy draw",
      "en": "Crystal Palace and Sunderland play out scrappy draw",
      "text_for_match": "Crystal Palace and Sunderland play out scrappy draw Crystal Palace and Sunderland play out a socreless draw at Selhurst Park. Crystal Palace and Sunderland play out a socreless draw at Selhurst Park.",
      "score_detail": {
        "fresh": 0.28781521559839957,
        "trust": 1,
        "relevance": 0.3333333333333333
      },
      "score": 0.506
    },
    {
      "id": "https://bbc.com/sport/football/articles/c62lz207081o?at_medium=RSS&at_campaign=rss",
      "ts": 1757780720000,
      "url": "https://bbc.com/sport/football/articles/c62lz207081o?at_medium=RSS&at_campaign=rss",
      "domain": "bbc.com",
      "trust": "bbc",
      "tags": [
        "復帰"
      ],
      "players": [],
      "ja": "Arsenal's 'scary show of strength' as Madueke shines",
      "en": "Arsenal's 'scary show of strength' as Madueke shines",
      "text_for_match": "Arsenal's 'scary show of strength' as Madueke shines Arsenal came into this season on the back of a busy summer transfer window where they spent around £250m and brought in eight players, and against Nottingham Forest the Gunners showed the reason behind such aggressive recruitment. Arsenal came into this season on the back of a busy summer transfer window where they spent around £250m and brought in eight players, and against Nottingham Forest the Gunners showed the reason behind such aggressive recruitment.",
      "score_detail": {
        "fresh": 0.2743502014233436,
        "trust": 1,
        "relevance": 0.3333333333333333
      },
      "score": 0.498
    },
    {
      "id": "https://bbc.com/sport/football/articles/c5yg082307ko?at_medium=RSS&at_campaign=rss",
      "ts": 1757838968000,
      "url": "https://bbc.com/sport/football/articles/c5yg082307ko?at_medium=RSS&at_campaign=rss",
      "domain": "bbc.com",
      "trust": "bbc",
      "tags": [],
      "players": [],
      "ja": "Ex-Man Utd striker Martial joins Monterrey",
      "en": "Ex-Man Utd striker Martial joins Monterrey",
      "text_for_match": "Ex-Man Utd striker Martial joins Monterrey France forward Anthony Martial, once the world's most expensive teenage player, joins Mexican side Monterrey. France forward Anthony Martial, once the world's most expensive teenage player, joins Mexican side Monterrey.",
      "score_detail": {
        "fresh": 0.32059254044793783,
        "trust": 1,
        "relevance": 0
      },
      "score": 0.492
    },
    {
      "id": "https://bbc.com/sport/football/articles/c5yv00l78rno?at_medium=RSS&at_campaign=rss",
      "ts": 1757831505000,
      "url": "https://bbc.com/sport/football/articles/c5yv00l78rno?at_medium=RSS&at_campaign=rss",
      "domain": "bbc.com",
      "trust": "bbc",
      "tags": [],
      "players": [],
      "ja": "Why is Barcelona's first home game not at Nou Camp? ",
      "en": "Why is Barcelona's first home game not at Nou Camp? ",
      "text_for_match": "Why is Barcelona's first home game not at Nou Camp?  BBC Sport's Ask Me Anything team look at why Barcelona's first home game of the season is not taking place at their Nou Camp home. BBC Sport's Ask Me Anything team look at why Barcelona's first home game of the season is not taking place at their Nou Camp home.",
      "score_detail": {
        "fresh": 0.31425777072907546,
        "trust": 1,
        "relevance": 0
      },
      "score": 0.489
    },
    {
      "id": "https://bbc.com/sport/football/articles/cd63jvlzzwdo?at_medium=RSS&at_campaign=rss",
      "ts": 1757798873000,
      "url": "https://bbc.com/sport/football/articles/cd63jvlzzwdo?at_medium=RSS&at_campaign=rss",
      "domain": "bbc.com",
      "trust": "bbc",
      "tags": [],
      "players": [],
      "ja": "Referees have had 'shocker' start to season - Maddison",
      "en": "Referees have had 'shocker' start to season - Maddison",
      "text_for_match": "Referees have had 'shocker' start to season - Maddison Tottenham's James Maddison says referees and video assistant referees (VAR) have had an \"absolute shocker of a start\" to the Premier League season. Tottenham's James Maddison says referees and video assistant referees (VAR) have had an \"absolute shocker of a start\" to the Premier League season.",
      "score_detail": {
        "fresh": 0.28799691490357704,
        "trust": 1,
        "relevance": 0
      },
      "score": 0.473
    },
    {
      "id": "https://bbc.com/sport/football/videos/c4gj2z9g335o?at_medium=RSS&at_campaign=rss",
      "ts": 1757798717000,
      "url": "https://bbc.com/sport/football/videos/c4gj2z9g335o?at_medium=RSS&at_campaign=rss",
      "domain": "bbc.com",
      "trust": "bbc",
      "tags": [],
      "players": [],
      "ja": "Spurs cruise to victory over 10-man West Ham",
      "en": "Spurs cruise to victory over 10-man West Ham",
      "text_for_match": "Spurs cruise to victory over 10-man West Ham Watch Premier League highlights as Tottenham take advantage of Tomas Soucek's red card as Thomas Frank's side cruise to a comfortable 3-0 win over West Ham at the London Stadium. Watch Premier League highlights as Tottenham take advantage of Tomas Soucek's red card as Thomas Frank's side cruise to a comfortable 3-0 win over West Ham at the London Stadium.",
      "score_detail": {
        "fresh": 0.2878767957362091,
        "trust": 1,
        "relevance": 0
      },
      "score": 0.473
    },
    {
      "id": "https://bbc.com/sport/football/articles/c79lg9zxyryo?at_medium=RSS&at_campaign=rss",
      "ts": 1757745143000,
      "url": "https://bbc.com/sport/football/articles/c79lg9zxyryo?at_medium=RSS&at_campaign=rss",
      "domain": "bbc.com",
      "trust": "bbc",
      "tags": [],
      "players": [],
      "ja": "Is the Premier League getting younger?",
      "en": "Is the Premier League getting younger?",
      "text_for_match": "Is the Premier League getting younger? BBC Sport's Ask Me Anything looks into why increasing number of teenagers and young players are playing in the Premier League this season. BBC Sport's Ask Me Anything looks into why increasing number of teenagers and young players are playing in the Premier League this season.",
      "score_detail": {
        "fresh": 0.24945190563754738,
        "trust": 1,
        "relevance": 0
      },
      "score": 0.45
    },
    {
      "id": "https://bbc.com/sport/football/articles/ckge8dwwdy7o?at_medium=RSS&at_campaign=rss",
      "ts": 1757688551000,
      "url": "https://bbc.com/sport/football/articles/ckge8dwwdy7o?at_medium=RSS&at_campaign=rss",
      "domain": "bbc.com",
      "trust": "bbc",
      "tags": [],
      "players": [],
      "ja": "Forest forward Silva joins Besiktas on loan ",
      "en": "Forest forward Silva joins Besiktas on loan ",
      "text_for_match": "Forest forward Silva joins Besiktas on loan  Nottingham Forest allow Portuguese forward Jota Silva to join Turkish club Besitkas on a season-long loan with an option to buy. Nottingham Forest allow Portuguese forward Jota Silva to join Turkish club Besitkas on a season-long loan with an option to buy. ",
      "score_detail": {
        "fresh": 0.21441834699633966,
        "trust": 1,
        "relevance": 0
      },
      "score": 0.429
    }
  ]
}